pysection/__init__.py
pysection/core/__init__.py
pysection/core/materials.py
pysection/core/mpl_plots.py
pysection/core/sect_utils.py
pysection/core/sections.py
pysection/utils/__init__.py
pysection/utils/checks.py
pysection/utils/dataread.py
pysection/utils/dataview.py
pysection/utils/reports.py
pysection/utils/slns.py
pysection-0.1.1.dist-info/LICENSE
pysection-0.1.1.dist-info/METADATA
pysection-0.1.1.dist-info/WHEEL
pysection-0.1.1.dist-info/top_level.txt
pysection-0.1.1.dist-info/RECORD
