Metadata-Version: 2.1
Name: pysection
Version: 0.1.1
Summary: Current version provides ULS Checks (NTC-2018) for RC sections based on FEM database
Home-page: https://github.com/chenguuu/pysection
Author: Cheng Lan
Author-email: lan@bolinaingegneria.com
License: MIT
Platform: UNKNOWN
Classifier: Development Status :: 3 - Alpha
Classifier: Intended Audience :: Developers
Classifier: Topic :: Software Development :: Build Tools
Classifier: License :: OSI Approved :: MIT License
Classifier: Programming Language :: Python :: 3.7
Requires-Python: >=3.7
Requires-Dist: shapely
Requires-Dist: numpy
Requires-Dist: pandas
Requires-Dist: xlrd
Requires-Dist: tables
Requires-Dist: matplotlib
Requires-Dist: plotly
